redflagdomains_scraper/__init__.py
redflagdomains_scraper/redflagdomains_scraper.py
redflagdomains_scraper/requirements.txt
redflagdomains_scraper-1.3.dist-info/METADATA
redflagdomains_scraper-1.3.dist-info/WHEEL
redflagdomains_scraper-1.3.dist-info/entry_points.txt
redflagdomains_scraper-1.3.dist-info/top_level.txt
redflagdomains_scraper-1.3.dist-info/RECORD
