Metadata-Version: 2.4
Name: redflagdomains_scraper
Version: 1.3
Summary: A simple Python script to scrape data from https://red.flag.domains/
Author-email: tdebize@mail.com
License-Expression: LGPL-3.0-or-later
Project-URL: Homepage, https://github.com/maaaaz/red.flag.domains_scraper
Keywords: red,flag,domains,red.flag.domains,spoofing,spoof,phishing
Classifier: Topic :: Security
Classifier: Programming Language :: Python :: 3
Requires-Python: >=3
Requires-Dist: cymruwhois
Requires-Dist: requests
Requires-Dist: beautifulsoup4
Requires-Dist: lxml
